MANIFEST.in
README.md
pyproject.toml
setup.py
clib_clustering/lidar_clustering.cpp
clib_clustering/lidar_clustering.pyx
lib_tracking/__init__.py
lib_tracking/lidar_tracking.py
pylidar2d.egg-info/PKG-INFO
pylidar2d.egg-info/SOURCES.txt
pylidar2d.egg-info/dependency_links.txt
pylidar2d.egg-info/top_level.txt