Metadata-Version: 2.1
Name: pylidar2d
Version: 0.1
Summary: Python tools for lidar 2d scans
Home-page: https://github.com/danieldugas/pylidar2d
Author: Daniel Dugas
License: UNKNOWN
Platform: UNKNOWN
